crias/__init__.py
crias/llms.py
crias/prompts.py
crias-0.1.2.dist-info/LICENSE
crias-0.1.2.dist-info/METADATA
crias-0.1.2.dist-info/WHEEL
crias-0.1.2.dist-info/RECORD
